[
  {
    "id": 1751094350887,
    "timestamp": "2025-06-28T07:05:50.887Z",
    "status": "new",
    "name": "DANG THUC",
    "company": "d",
    "phone": "0876840209",
    "email": "thucdangvan1999@gmail.com",
    "service": "nuoi-ca",
    "message": "đ"
  },
  {
    "id": 1751098138441,
    "timestamp": "2025-06-28T08:08:58.441Z",
    "status": "new",
    "name": "DANG THUC",
    "company": "d",
    "phone": "0876840209",
    "email": "thucdangvan020999@gmail.com",
    "service": "nuoi-ca",
    "message": "dđ"
  },
  {
    "id": 1751098180694,
    "timestamp": "2025-06-28T08:09:40.694Z",
    "status": "new",
    "name": "DANG THUC",
    "company": "d",
    "phone": "0876840209",
    "email": "thucdangvan020999@gmail.com",
    "service": "nuoi-ca",
    "message": "yh"
  },
  {
    "id": 1751200418771,
    "timestamp": "2025-06-29T12:33:38.771Z",
    "status": "new",
    "name": "fhhufd",
    "company": "fhhufd`",
    "phone": "0112555555",
    "email": "thucdang@gmail.com",
    "service": "nuoi-cua",
    "message": "dfgdafdf"
  }
]